diglett/__init__.py
diglett/eda.py
diglett/group.py
diglett/insist.py
diglett/join.py
diglett/output.py
diglett/transform.py
diglett/utils.py
diglett-0.2.0.dist-info/LICENSE
diglett-0.2.0.dist-info/WHEEL
diglett-0.2.0.dist-info/METADATA
diglett-0.2.0.dist-info/RECORD
