Metadata-Version: 2.1
Name: diglett
Version: 0.2.0
Summary: Tools for data wrangling.
Author: Geoff Ruddock
Author-email: geoff@ruddock.ca
Requires-Python: >=3.8.6,<4.0.0
Classifier: Programming Language :: Python :: 3
Classifier: Programming Language :: Python :: 3.10
Classifier: Programming Language :: Python :: 3.9
Requires-Dist: Jinja2 (>=3.0.2,<4.0.0)
Requires-Dist: ipython (>=7.26.0,<8.0.0)
Requires-Dist: matplotlib (>=3.4.2,<4.0.0)
Requires-Dist: numpy (==1.19.5)
Requires-Dist: pandas (==1.3.0)
Requires-Dist: seaborn (>=0.11.1,<0.12.0)
Project-URL: Documentation, https://diglett.readthedocs.io
